LICENSE
django_custom_commands/__init__.py
django_custom_commands/management.py
django_custom_commands-0.1.0.dist-info/LICENSE
django_custom_commands-0.1.0.dist-info/METADATA
django_custom_commands-0.1.0.dist-info/WHEEL
django_custom_commands-0.1.0.dist-info/RECORD
